riimut/__init__.py
riimut/elder_futhark.py
riimut/futhorc.py
riimut/medieval_futhork.py
riimut/staveless_futhark.py
riimut/transform.py
riimut/younger_futhark.py
riimut/dialects/__init__.py
riimut/dialects/elder_futhark/__init__.py
riimut/dialects/elder_futhark/letters.py
riimut/dialects/elder_futhark/runes.py
riimut/dialects/futhorc/__init__.py
riimut/dialects/futhorc/letters.py
riimut/dialects/futhorc/runes.py
riimut/dialects/medieval_futhork/__init__.py
riimut/dialects/medieval_futhork/letters.py
riimut/dialects/medieval_futhork/runes.py
riimut/dialects/staveless_futhark/__init__.py
riimut/dialects/staveless_futhark/letters.py
riimut/dialects/staveless_futhark/runes.py
riimut/dialects/younger_futhark/__init__.py
riimut/dialects/younger_futhark/letters.py
riimut/dialects/younger_futhark/runes.py
riimut-1.3.0.dist-info/LICENSE
riimut-1.3.0.dist-info/METADATA
riimut-1.3.0.dist-info/WHEEL
riimut-1.3.0.dist-info/top_level.txt
riimut-1.3.0.dist-info/RECORD
