Metadata-Version: 2.1
Name: riimut
Version: 1.3.0
Summary: Transform latin letters to runes and vice versa
Home-page: https://github.com/stscoundrel/riimut-py
Author: stscoundrel
Requires-Python: >=3.9
License-File: LICENSE
